phygitalism_config/__init__.py
phygitalism_config/__main__.py
phygitalism_config/config.py
phygitalism_config/exceptions.py
phygitalism_config/generator.py
phygitalism_config/import_finder.py
phygitalism_config/import_loader.py
phygitalism_config/loaders_constants.py
phygitalism_config/special_types/__init__.py
phygitalism_config/special_types/realtime.py
phygitalism_config/special_types/required.py
phygitalism_config/type_caster.py
phygitalism_config-0.1.15.dist-info/entry_points.txt
phygitalism_config-0.1.15.dist-info/WHEEL
phygitalism_config-0.1.15.dist-info/METADATA
phygitalism_config-0.1.15.dist-info/RECORD
