Metadata-Version: 2.1
Name: phygitalism-config
Version: 0.1.15
Summary: 
Author: Phygitalism
Requires-Python: >=3.7,<4.0
Classifier: Programming Language :: Python :: 3
Classifier: Programming Language :: Python :: 3.7
Classifier: Programming Language :: Python :: 3.8
Classifier: Programming Language :: Python :: 3.9
Requires-Dist: pydantic (>=1.8.2,<2.0.0)
Requires-Dist: toml (>=0.10.2,<0.11.0)
Requires-Dist: typing-inspect (>=0.6.0,<0.7.0)
